{"書名":"優勝數學重點評量（國小5年級）","書籍網站":"https:\/\/www.kingstone.com.tw\/\/basic\/2015232005004?zone=book&lid=book_class3_tel&actid=book_class3_tel","作者":"數學資優教材編寫小組","出版社":"人類文化  ","ISBN":4715443019071,"圖片網址":"https:\/\/cdn.kingstone.com.tw\/book\/images\/product\/20152\/2015232005004\/2015232005004b.jpg","書籍簡介":"\r\n\r\n1.本書依據教育部民國九十四年頒定的「九年一貫數學領域綱要」編寫而成，其中「數學領域分年細目」的內容完全包括在內。故不論採用「康軒」、「南一」、「翰林」、「部編」……各版本的數學教科書，均適用本書當作課外輔助教材。2.本書就是為了讓孩子迅速、有效的學習而設計的。將5年級必須學習的所有學習指標，整理成20個單元，又在每個單元中，依學生的學習狀況，歸納出學習重點，透過詳盡的題型，讓學生精熟練習，達成學習目標。3.本書包含二大特色：(1)學習評量：依學習重點分步驟進行評量，完整的題型，讓學生學習不遺漏。(2)單元評量：提供每個單元的綜合評量，將各個單元的概念統整應用。4.本書為延伸應用的最佳題本，除了完整學習所有教學重點外，也可搭配「優勝數學重點學習」，2頁重點評量搭配2頁重點學習使用，也可運用「優勝數學120回測驗」作為複習，熟練與深入的練習，幫孩子建構良好的數學基礎。\r\n                    \r\n"}
